vaspvis/__init__.py
vaspvis/band.py
vaspvis/band_helpers.py
vaspvis/charge.py
vaspvis/dos.py
vaspvis/dos_helpers.py
vaspvis/standard.py
vaspvis/stm.py
vaspvis/utils.py
vaspvis/warnings_config.py
vaspvis/workflow.py
vaspvis/passivator_utils/__init__.py
vaspvis/passivator_utils/passivator_utils.py
vaspvis/unfold/__init__.py
vaspvis/unfold/convert.py
vaspvis/unfold/unfold.py
vaspvis/unfold/vasp_constant.py
vaspvis/unfold/vaspwfc.py
vaspvis-1.3.6.dist-info/licenses/LICENSE.txt
vaspvis-1.3.6.dist-info/METADATA
vaspvis-1.3.6.dist-info/WHEEL
vaspvis-1.3.6.dist-info/top_level.txt
vaspvis-1.3.6.dist-info/RECORD
