Metadata-Version: 2.4
Name: vaspvis
Version: 1.3.6
Summary: A highly flexible and customizable library for visualizing electronic structure data from VASP calculations
Home-page: https://github.com/caizefeng/vaspvis
Author: Derek Dardzinski
Maintainer: Zefeng Cai
License: MIT
License-File: LICENSE.txt
Requires-Dist: pyprocar==5.6.6
Requires-Dist: scipy
Requires-Dist: pymatgen
Requires-Dist: matplotlib
Requires-Dist: numpy
Requires-Dist: pandas
Requires-Dist: ase
Requires-Dist: pychemia
Requires-Dist: fastdtw
Requires-Dist: scikit-learn
Dynamic: author
Dynamic: description
Dynamic: description-content-type
Dynamic: home-page
Dynamic: license
Dynamic: license-file
Dynamic: maintainer
Dynamic: requires-dist
Dynamic: summary
